{
    "chapter_name": "",
    "vol": 1,
    "chap": 2.0,
    "language": "vi",
    "reading_progress": 0,
    "images": [
        "https://iili.io/3tFTINj.jpg",
        "https://iili.io/3tFTnSe.jpg",
        "https://iili.io/3tFTxHu.jpg",
        "https://iili.io/3tFTzAb.jpg",
        "https://iili.io/3tFTAoQ.jpg",
        "https://iili.io/3tFTRVV.jpg",
        "https://iili.io/3tFT5iB.jpg",
        "https://iili.io/3tFTYKP.jpg",
        "https://iili.io/3tFT0Hg.jpg",
        "https://iili.io/3tFTEOJ.jpg",
        "https://iili.io/3tFTGDv.jpg",
        "https://iili.io/3tFTVxR.jpg",
        "https://iili.io/3tFTjfI.jpg",
        "https://iili.io/3tFTwlt.jpg",
        "https://iili.io/3tFTNUX.jpg",
        "https://iili.io/3tFTeJn.jpg",
        "https://iili.io/3tFTvOG.jpg",
        "https://iili.io/3tFTUx4.jpg",
        "https://iili.io/3tFTgWl.jpg",
        "https://iili.io/3tFTrs2.jpg",
        "https://iili.io/3tFTLJe.jpg",
        "https://iili.io/3tFTZOb.jpg",
        "https://iili.io/3tFTbzx.jpg",
        "https://iili.io/3tFTtbj.jpg",
        "https://iili.io/3tFTpsV.jpg",
        "https://iili.io/3tFu9qB.jpg",
        "https://iili.io/3tFuH0P.jpg",
        "https://iili.io/3tFuJg1.jpg",
        "https://iili.io/3tFu2dF.jpg",
        "https://iili.io/3tFu35g.jpg",
        "https://iili.io/3tFuFea.jpg",
        "https://iili.io/3tFuKmJ.jpg",
        "https://iili.io/3tFuBXR.jpg",
        "https://iili.io/3tFuCsp.jpg",
        "https://iili.io/3tFuoqN.jpg"
    ],
    "comments": [],
    "one_shot": false,
    "created_at": "2025-05-23T20:48:32Z",
    "updated_at": "2025-05-23T20:48:32Z"
}